krakow/__init__.py
krakow/utils.py
krakow-0.2.1.dist-info/WHEEL
krakow-0.2.1.dist-info/METADATA
krakow-0.2.1.dist-info/RECORD
