Metadata-Version: 2.1
Name: krakow
Version: 0.2.1
Summary: Well balanced hierarchical graph clustering
Author: Filip Sondej
Author-email: filipsondej@protonmail.com
Requires-Python: >=3.8,<4.0
Classifier: Programming Language :: Python :: 3
Classifier: Programming Language :: Python :: 3.8
Classifier: Programming Language :: Python :: 3.9
Classifier: Programming Language :: Python :: 3.10
Requires-Dist: matplotlib (>=3.4.2,<4.0.0)
Requires-Dist: networkx (>=2.6.1,<3.0.0)
Requires-Dist: numpy (>=1.21.1,<2.0.0)
